mfd_base_tool/__init__.py
mfd_base_tool/exceptions.py
mfd_base_tool/mfd_base_tool.py
mfd_base_tool-2.7.0.dist-info/licenses/AUTHORS.md
mfd_base_tool-2.7.0.dist-info/licenses/LICENSE.md
mfd_base_tool-2.7.0.dist-info/METADATA
mfd_base_tool-2.7.0.dist-info/WHEEL
mfd_base_tool-2.7.0.dist-info/top_level.txt
mfd_base_tool-2.7.0.dist-info/RECORD
