Metadata-Version: 2.4
Name: mfd-base-tool
Version: 2.7.0
Summary: Module that contains abstraction of tool in Modular Framework Design (MFD).
Project-URL: Homepage, https://github.com/intel/mfd
Project-URL: Repository, https://github.com/intel/mfd-tool
Project-URL: Issues, https://github.com/intel/mfd-tool/issues
Project-URL: Changelog, https://github.com/intel/mfd-tool/blob/main/CHANGELOG.md
Requires-Python: <3.14,>=3.10
License-File: LICENSE.md
License-File: AUTHORS.md
Requires-Dist: mfd-typing<2,>=1.23.0
Requires-Dist: mfd-common-libs<2,>=1.11.0
Dynamic: license-file
